qtqp/__init__.py
qtqp/direct.py
qtqp-0.0.1.dist-info/METADATA
qtqp-0.0.1.dist-info/WHEEL
qtqp-0.0.1.dist-info/top_level.txt
qtqp-0.0.1.dist-info/RECORD
