Metadata-Version: 2.4
Name: qtqp
Version: 0.0.1
Summary: The 'cutie' QP solver.
Author-email: Brendan O'Donoghue <bodonoghue85@gmail.com>
License: 
Requires-Python: >=3.9
Requires-Dist: numpy>=1.23
Requires-Dist: scipy>=1.9
Provides-Extra: test
Requires-Dist: pytest; extra == "test"
